schwab/__init__.py
schwab/_token.py
schwab/client.py
schwab/urls.py
schwab/utils.py
schwab/websocket.py
schwab/enums/__init__.py
schwab/enums/base.py
schwab/enums/order.py
schwab/enums/pricehistory.py
schwab/enums/transaction.py
schwab/enums/websocket.py
schwab/models/__init__.py
schwab/models/accounts.py
schwab/models/meta.py
schwab/models/orders.py
schwab/models/positions.py
schwab/models/quotes.py
schwab/models/transactions.py
schwab/models/userpreferences.py
schwab/providers/__init__.py
schwab/providers/abstract.py
schwab/providers/base.py
schwab/providers/json.py
schwab/providers/mysql.py
schwab/providers/redis.py
schwab/providers/sqlite.py
my_schwab-1.1.5.dist-info/LICENSE
my_schwab-1.1.5.dist-info/METADATA
my_schwab-1.1.5.dist-info/WHEEL
my_schwab-1.1.5.dist-info/top_level.txt
my_schwab-1.1.5.dist-info/RECORD
