Metadata-Version: 2.1
Name: my-schwab
Version: 1.1.5
Summary: A Python package to interact with the Charles Schwab API.
Author-email: John Gaddis <normlman@live.com>
Classifier: Programming Language :: Python :: 3
Classifier: License :: OSI Approved :: GNU General Public License v3 or later (GPLv3+)
Classifier: Operating System :: OS Independent
Requires-Python: >=3.10
License-File: LICENSE
Requires-Dist: aiohttp[speedups]
Requires-Dist: async-timeout
Requires-Dist: requests
Requires-Dist: orjson
Requires-Dist: pysynchronizer
Requires-Dist: python-dateutil
Requires-Dist: websockets
Provides-Extra: all
Requires-Dist: aiohttp[speedups] ; extra == 'all'
Requires-Dist: async-timeout ; extra == 'all'
Requires-Dist: orjson ; extra == 'all'
Requires-Dist: pysynchronizer ; extra == 'all'
Requires-Dist: pymysql ; extra == 'all'
Requires-Dist: redis ; extra == 'all'
Requires-Dist: websockets ; extra == 'all'
Provides-Extra: mysql
Requires-Dist: pymysql ; extra == 'mysql'
Provides-Extra: redis
Requires-Dist: redis ; extra == 'redis'
Provides-Extra: websocket
Requires-Dist: websockets ; extra == 'websocket'
